edpy/__init__.py
edpy/__main__.py
edpy/iris.py
edpy-0.1.1.dist-info/LICENSE
edpy-0.1.1.dist-info/METADATA
edpy-0.1.1.dist-info/WHEEL
edpy-0.1.1.dist-info/entry_points.txt
edpy-0.1.1.dist-info/top_level.txt
edpy-0.1.1.dist-info/RECORD
