Metadata-Version: 2.1
Name: edpy
Version: 0.1.1
Summary: eduard93 python utils
Author: eduard93
License: MIT License        
Project-URL: repository, https://github.com/eduard93/edpy
Project-URL: documentation, https://github.com/eduard93/edpy
Keywords: utils
Classifier: License :: OSI Approved :: MIT License
Classifier: Programming Language :: Python
Classifier: Programming Language :: Python :: 3
Requires-Python: >=3.2
License-File: LICENSE
Provides-Extra: build
Requires-Dist: build ; extra == 'build'
Provides-Extra: dev
Requires-Dist: bumpver ; extra == 'dev'
